__init__.py
wgs_est_converter/__init__.py
wgs_est_converter/main.py
wgs_est_converter-1.5.7.dist-info/LICENSE
wgs_est_converter-1.5.7.dist-info/METADATA
wgs_est_converter-1.5.7.dist-info/WHEEL
wgs_est_converter-1.5.7.dist-info/top_level.txt
wgs_est_converter-1.5.7.dist-info/RECORD
