Metadata-Version: 2.1
Name: wgs-est-converter
Version: 1.5.7
Summary: A small example package
Author-email: Mahdi Rasoulinezhad <maraso@ttu.ee>
Classifier: Programming Language :: Python :: 3
Classifier: License :: OSI Approved :: MIT License
Classifier: Operating System :: OS Independent
Requires-Python: >=3.8
License-File: LICENSE
Requires-Dist: pyproj
Requires-Dist: Shapely
